{"nodes": [{"id": "src_components_ui_offline_banner_tsx", "label": "offline-banner.tsx", "file_type": "code", "source_file": "src/components/ui/offline-banner.tsx", "source_location": "L1"}, {"id": "offline_banner_offlinebanner", "label": "OfflineBanner()", "file_type": "code", "source_file": "src/components/ui/offline-banner.tsx", "source_location": "L7"}], "edges": [{"source": "src_components_ui_offline_banner_tsx", "target": "react", "relation": "imports_from", "confidence": "EXTRACTED", "source_file": "src/components/ui/offline-banner.tsx", "source_location": "L3", "weight": 1.0}, {"source": "src_components_ui_offline_banner_tsx", "target": "lucide_react", "relation": "imports_from", "confidence": "EXTRACTED", "source_file": "src/components/ui/offline-banner.tsx", "source_location": "L4", "weight": 1.0}, {"source": "src_components_ui_offline_banner_tsx", "target": "offline", "relation": "imports_from", "confidence": "EXTRACTED", "source_file": "src/components/ui/offline-banner.tsx", "source_location": "L5", "weight": 1.0}, {"source": "src_components_ui_offline_banner_tsx", "target": "offline_banner_offlinebanner", "relation": "contains", "confidence": "EXTRACTED", "source_file": "src/components/ui/offline-banner.tsx", "source_location": "L7", "weight": 1.0}], "raw_calls": [{"caller_nid": "offline_banner_offlinebanner", "callee": "useState", "source_file": "src/components/ui/offline-banner.tsx", "source_location": "L8"}, {"caller_nid": "offline_banner_offlinebanner", "callee": "useState", "source_file": "src/components/ui/offline-banner.tsx", "source_location": "L9"}, {"caller_nid": "offline_banner_offlinebanner", "callee": "useState", "source_file": "src/components/ui/offline-banner.tsx", "source_location": "L10"}, {"caller_nid": "offline_banner_offlinebanner", "callee": "useEffect", "source_file": "src/components/ui/offline-banner.tsx", "source_location": "L12"}]}